cmsplugin_css_background/__init__.py
cmsplugin_css_background/cms_plugins.py
cmsplugin_css_background/models.py
cmsplugin_css_background/migrations/0001_initial.py
cmsplugin_css_background/migrations/0002_filercssbackground.py
cmsplugin_css_background/migrations/0003_color_field_default.py
cmsplugin_css_background/migrations/0004_optional_image_field.py
cmsplugin_css_background/migrations/0005_update_defaults.py
cmsplugin_css_background/migrations/__init__.py
cmsplugin_css_background/templates/cmsplugin_css_background/css-background.html
cmsplugin_css_background-0.2.0.dist-info/LICENSE
cmsplugin_css_background-0.2.0.dist-info/METADATA
cmsplugin_css_background-0.2.0.dist-info/WHEEL
cmsplugin_css_background-0.2.0.dist-info/top_level.txt
cmsplugin_css_background-0.2.0.dist-info/RECORD
