Metadata-Version: 2.1
Name: cmsplugin-css-background
Version: 0.2.0
Summary: A django CMS plugin for managing CSS background styles
Home-page: https://github.com/alexmalykh/cmsplugin-css-background
Author: Alex Malykh
Author-email: a2m.dev@yandex.ru
License: MIT License
Classifier: Development Status :: 4 - Beta
Classifier: Environment :: Web Environment
Classifier: Framework :: Django
Classifier: Intended Audience :: Developers
Classifier: License :: OSI Approved :: MIT License
Classifier: Programming Language :: Python
Classifier: Programming Language :: Python :: 2.7
Classifier: Programming Language :: Python :: 3.6
Classifier: Topic :: Internet :: WWW/HTTP :: Dynamic Content
Classifier: Topic :: Internet :: WWW/HTTP :: Site Management
Classifier: Topic :: Software Development :: Libraries :: Python Modules
License-File: LICENSE
Requires-Dist: django-cms (<4.0,>=3.3)
Requires-Dist: django-sekizai (>=0.7)
